{
  "title": "RSS",
  "icon": "",
  "id": "01FQC300GGWCA7A8H0SXY6P9FG",
  "description": "Mulighed for at vise et rss feed.",
  "resources": {
    "component": "https://raw.githubusercontent.com/kkos2/display-templates/main/build/rss.js?ts=1679250386190",
    "admin": "https://raw.githubusercontent.com/kkos2/display-templates/main/build/rss-admin.json?ts=1679250386190",
    "schema": "https://raw.githubusercontent.com/kkos2/display-templates/main/build/rss-schema.json",
    "assets": [],
    "options": {},
    "content": {}
  }
}
